[
    {
        "id": "c73d35828f3586b6",
        "type": "mqtt-broker",
        "name": "",
        "broker": "broker.hivemq.com",
        "port": "1883",
        "clientid": "",
        "autoConnect": true,
        "usetls": false,
        "protocolVersion": "4",
        "keepalive": "60",
        "cleansession": true,
        "autoUnsubscribe": true,
        "birthTopic": "",
        "birthQos": "0",
        "birthPayload": "",
        "birthMsg": {},
        "closeTopic": "",
        "closeQos": "0",
        "closePayload": "",
        "closeMsg": {},
        "willTopic": "",
        "willQos": "0",
        "willPayload": "",
        "willMsg": {},
        "userProps": "",
        "sessionExpiry": ""
    },
    {
        "id": "ui_base_modern",
        "type": "ui_base",
        "theme": {
            "name": "theme-custom",
            "lightTheme": {
                "default": "#0094CE",
                "baseColor": "#0094CE",
                "baseFont": "-apple-system,BlinkMacSystemFont,Segoe UI,Roboto,Oxygen-Sans,Ubuntu,Cantarell,Helvetica Neue,sans-serif",
                "edited": false
            },
            "darkTheme": {
                "default": "#097479",
                "baseColor": "#097479",
                "baseFont": "-apple-system,BlinkMacSystemFont,Segoe UI,Roboto,Oxygen-Sans,Ubuntu,Cantarell,Helvetica Neue,sans-serif",
                "edited": false
            },
            "customTheme": {
                "name": "Smart Greenhouse Pro",
                "default": "#4B7399",
                "baseColor": "#0a0e27",
                "baseFont": "'Roboto', 'Segoe UI', sans-serif"
            },
            "themeState": {
                "base-color": {
                    "default": "#097479",
                    "value": "#0a0e27",
                    "edited": true
                },
                "page-titlebar-backgroundColor": {
                    "value": "#0a0e27",
                    "edited": true
                },
                "page-backgroundColor": {
                    "value": "#141b2d",
                    "edited": true
                },
                "page-sidebar-backgroundColor": {
                    "value": "#0a0e27",
                    "edited": true
                },
                "group-textColor": {
                    "value": "#00f5ff",
                    "edited": true
                },
                "group-borderColor": {
                    "value": "#00f5ff",
                    "edited": true
                },
                "group-backgroundColor": {
                    "value": "#1a1f35",
                    "edited": true
                },
                "widget-textColor": {
                    "value": "#e8e8e8",
                    "edited": true
                },
                "widget-backgroundColor": {
                    "value": "#0f1729",
                    "edited": true
                },
                "widget-borderColor": {
                    "value": "#1e2942",
                    "edited": true
                },
                "base-font": {
                    "value": "'Roboto', 'Segoe UI', sans-serif"
                }
            },
            "angularTheme": {
                "primary": "indigo",
                "accents": "blue",
                "warn": "red",
                "background": "grey",
                "palette": "light"
            }
        },
        "site": {
            "name": "🌱 Smart Greenhouse Dashboard",
            "hideToolbar": "false",
            "allowSwipe": "false",
            "lockMenu": "false",
            "allowTempTheme": "true",
            "dateFormat": "DD/MM/YYYY",
            "sizes": {
                "sx": 48,
                "sy": 48,
                "gx": 6,
                "gy": 6,
                "cx": 6,
                "cy": 6,
                "px": 0,
                "py": 0
            }
        }
    },
    {
        "id": "main_tab",
        "type": "ui_tab",
        "name": "🏡 Home",
        "icon": "fa-leaf",
        "order": 1,
        "disabled": false,
        "hidden": false
    },
    {
        "id": "group_climate",
        "type": "ui_group",
        "name": "🌡️ Climate Control",
        "tab": "main_tab",
        "order": 1,
        "disp": true,
        "width": "12",
        "collapse": false,
        "className": ""
    },
    {
        "id": "group_environment",
        "type": "ui_group",
        "name": "💡 Environment",
        "tab": "main_tab",
        "order": 2,
        "disp": true,
        "width": "12",
        "collapse": false,
        "className": ""
    },
    {
        "id": "group_systems",
        "type": "ui_group",
        "name": "⚡ Active Systems",
        "tab": "main_tab",
        "order": 3,
        "disp": true,
        "width": "12",
        "collapse": false,
        "className": ""
    },
    {
        "id": "group_trends",
        "type": "ui_group",
        "name": "📊 Real-Time Analytics",
        "tab": "main_tab",
        "order": 4,
        "disp": true,
        "width": "12",
        "collapse": false,
        "className": ""
    },
    {
        "id": "group_controls",
        "type": "ui_group",
        "name": "🎮 Manual Override",
        "tab": "main_tab",
        "order": 5,
        "disp": true,
        "width": "12",
        "collapse": false,
        "className": ""
    },
    {
        "id": "e6ecd1a3fd06e046",
        "type": "tab",
        "label": "Greenhouse System",
        "disabled": false,
        "info": "",
        "env": []
    },
    {
        "id": "mqtt_temp_in",
        "type": "mqtt in",
        "z": "e6ecd1a3fd06e046",
        "name": "",
        "topic": "serre/temperature",
        "qos": "2",
        "datatype": "auto-detect",
        "broker": "c73d35828f3586b6",
        "nl": false,
        "rap": true,
        "rh": 0,
        "inputs": 0,
        "x": 130,
        "y": 80,
        "wires": [["gauge_temp", "chart_temp"]]
    },
    {
        "id": "gauge_temp",
        "type": "ui_gauge",
        "z": "e6ecd1a3fd06e046",
        "name": "",
        "group": "group_climate",
        "order": 1,
        "width": "4",
        "height": "4",
        "gtype": "donut",
        "title": "Temperature",
        "label": "°C",
        "format": "{{value | number:1}}",
        "min": 0,
        "max": "50",
        "colors": ["#00ffaa","#ffeb3b","#ff1744"],
        "seg1": "20",
        "seg2": "30",
        "diff": false,
        "className": "",
        "x": 380,
        "y": 80,
        "wires": []
    },
    {
        "id": "chart_temp",
        "type": "ui_chart",
        "z": "e6ecd1a3fd06e046",
        "name": "",
        "group": "group_trends",
        "order": 1,
        "width": "6",
        "height": "5",
        "label": "Temperature",
        "chartType": "line",
        "legend": "false",
        "xformat": "HH:mm:ss",
        "interpolate": "smooth",
        "nodata": "⏳ Waiting for data...",
        "dot": false,
        "ymin": "0",
        "ymax": "50",
        "removeOlder": 1,
        "removeOlderPoints": "",
        "removeOlderUnit": "3600",
        "cutout": 0,
        "useOneColor": false,
        "useUTC": false,
        "colors": ["#ff1744","#f50057","#d500f9","#651fff","#3d5afe","#2979ff","#00b0ff","#00e5ff","#1de9b6"],
        "outputs": 1,
        "useDifferentColor": false,
        "className": "",
        "x": 380,
        "y": 480,
        "wires": [[]]
    },
    {
        "id": "mqtt_humidity_in",
        "type": "mqtt in",
        "z": "e6ecd1a3fd06e046",
        "name": "",
        "topic": "serre/humidity",
        "qos": "2",
        "datatype": "auto-detect",
        "broker": "c73d35828f3586b6",
        "nl": false,
        "rap": true,
        "rh": 0,
        "inputs": 0,
        "x": 130,
        "y": 140,
        "wires": [["gauge_humidity", "chart_humidity"]]
    },
    {
        "id": "gauge_humidity",
        "type": "ui_gauge",
        "z": "e6ecd1a3fd06e046",
        "name": "",
        "group": "group_climate",
        "order": 2,
        "width": "4",
        "height": "4",
        "gtype": "donut",
        "title": "Humidity",
        "label": "%",
        "format": "{{value | number:1}}",
        "min": 0,
        "max": "100",
        "colors": ["#ff1744","#ffeb3b","#00ffaa"],
        "seg1": "30",
        "seg2": "60",
        "diff": false,
        "className": "",
        "x": 380,
        "y": 140,
        "wires": []
    },
    {
        "id": "chart_humidity",
        "type": "ui_chart",
        "z": "e6ecd1a3fd06e046",
        "name": "",
        "group": "group_trends",
        "order": 2,
        "width": "6",
        "height": "5",
        "label": "Humidity",
        "chartType": "line",
        "legend": "false",
        "xformat": "HH:mm:ss",
        "interpolate": "smooth",
        "nodata": "⏳ Waiting for data...",
        "dot": false,
        "ymin": "0",
        "ymax": "100",
        "removeOlder": 1,
        "removeOlderPoints": "",
        "removeOlderUnit": "3600",
        "cutout": 0,
        "useOneColor": false,
        "useUTC": false,
        "colors": ["#00e5ff","#18ffff","#64ffda","#69f0ae","#b2ff59","#eeff41","#ffff00","#ffd600"],
        "outputs": 1,
        "useDifferentColor": false,
        "className": "",
        "x": 380,
        "y": 540,
        "wires": [[]]
    },
    {
        "id": "mqtt_light_in",
        "type": "mqtt in",
        "z": "e6ecd1a3fd06e046",
        "name": "",
        "topic": "serre/light",
        "qos": "2",
        "datatype": "auto-detect",
        "broker": "c73d35828f3586b6",
        "nl": false,
        "rap": true,
        "rh": 0,
        "inputs": 0,
        "x": 120,
        "y": 200,
        "wires": [["gauge_light", "chart_light"]]
    },
    {
        "id": "gauge_light",
        "type": "ui_gauge",
        "z": "e6ecd1a3fd06e046",
        "name": "",
        "group": "group_environment",
        "order": 1,
        "width": "4",
        "height": "4",
        "gtype": "donut",
        "title": "Light Intensity",
        "label": "lux",
        "format": "{{value | number:0}}",
        "min": 0,
        "max": "4095",
        "colors": ["#ff1744","#ffeb3b","#00ffaa"],
        "seg1": "1000",
        "seg2": "2000",
        "diff": false,
        "className": "",
        "x": 380,
        "y": 200,
        "wires": []
    },
    {
        "id": "chart_light",
        "type": "ui_chart",
        "z": "e6ecd1a3fd06e046",
        "name": "",
        "group": "group_trends",
        "order": 3,
        "width": "6",
        "height": "5",
        "label": "Light Intensity",
        "chartType": "line",
        "legend": "false",
        "xformat": "HH:mm:ss",
        "interpolate": "smooth",
        "nodata": "⏳ Waiting for data...",
        "dot": false,
        "ymin": "0",
        "ymax": "4095",
        "removeOlder": 1,
        "removeOlderPoints": "",
        "removeOlderUnit": "3600",
        "cutout": 0,
        "useOneColor": false,
        "useUTC": false,
        "colors": ["#ffeb3b","#ffc400","#ffab00","#ff6f00","#ff3d00","#dd2c00"],
        "outputs": 1,
        "useDifferentColor": false,
        "className": "",
        "x": 380,
        "y": 600,
        "wires": [[]]
    },
    {
        "id": "mqtt_co2_in",
        "type": "mqtt in",
        "z": "e6ecd1a3fd06e046",
        "name": "",
        "topic": "serre/co2",
        "qos": "2",
        "datatype": "auto-detect",
        "broker": "c73d35828f3586b6",
        "nl": false,
        "rap": true,
        "rh": 0,
        "inputs": 0,
        "x": 120,
        "y": 260,
        "wires": [["gauge_co2", "chart_co2"]]
    },
    {
        "id": "gauge_co2",
        "type": "ui_gauge",
        "z": "e6ecd1a3fd06e046",
        "name": "",
        "group": "group_environment",
        "order": 2,
        "width": "4",
        "height": "4",
        "gtype": "donut",
        "title": "CO2 Level",
        "label": "ppm",
        "format": "{{value | number:0}}",
        "min": 0,
        "max": "4095",
        "colors": ["#00ffaa","#ffeb3b","#ff1744"],
        "seg1": "1500",
        "seg2": "2500",
        "diff": false,
        "className": "",
        "x": 370,
        "y": 260,
        "wires": []
    },
    {
        "id": "chart_co2",
        "type": "ui_chart",
        "z": "e6ecd1a3fd06e046",
        "name": "",
        "group": "group_trends",
        "order": 4,
        "width": "6",
        "height": "5",
        "label": "CO2 Level",
        "chartType": "line",
        "legend": "false",
        "xformat": "HH:mm:ss",
        "interpolate": "smooth",
        "nodata": "⏳ Waiting for data...",
        "dot": false,
        "ymin": "0",
        "ymax": "4095",
        "removeOlder": 1,
        "removeOlderPoints": "",
        "removeOlderUnit": "3600",
        "cutout": 0,
        "useOneColor": false,
        "useUTC": false,
        "colors": ["#00ffaa","#00e676","#76ff03","#c6ff00","#f4ff81","#ffeb3b"],
        "outputs": 1,
        "useDifferentColor": false,
        "className": "",
        "x": 370,
        "y": 660,
        "wires": [[]]
    },
    {
        "id": "mqtt_rain_in",
        "type": "mqtt in",
        "z": "e6ecd1a3fd06e046",
        "name": "",
        "topic": "serre/rain",
        "qos": "2",
        "datatype": "auto-detect",
        "broker": "c73d35828f3586b6",
        "nl": false,
        "rap": true,
        "rh": 0,
        "inputs": 0,
        "x": 120,
        "y": 320,
        "wires": [["text_rain"]]
    },
    {
        "id": "text_rain",
        "type": "ui_text",
        "z": "e6ecd1a3fd06e046",
        "group": "group_environment",
        "order": 3,
        "width": "4",
        "height": "2",
        "name": "",
        "label": "🌧️ Rain Detection",
        "format": "<div style='font-size:32px;text-align:center;padding:15px;font-weight:500'>{{msg.payload==\"1\"?\"<span style='color:#00e5ff'>☔ RAIN</span>\":\"<span style='color:#666'>☀️ DRY</span>\"}}</div>",
        "layout": "row-center",
        "className": "",
        "x": 360,
        "y": 320,
        "wires": []
    },
    {
        "id": "mqtt_irrigation_in",
        "type": "mqtt in",
        "z": "e6ecd1a3fd06e046",
        "name": "",
        "topic": "serre/irrigation",
        "qos": "2",
        "datatype": "auto-detect",
        "broker": "c73d35828f3586b6",
        "nl": false,
        "rap": true,
        "rh": 0,
        "inputs": 0,
        "x": 130,
        "y": 760,
        "wires": [["text_irrigation"]]
    },
    {
        "id": "text_irrigation",
        "type": "ui_text",
        "z": "e6ecd1a3fd06e046",
        "group": "group_systems",
        "order": 1,
        "width": "3",
        "height": "1",
        "name": "",
        "label": "💧 Irrigation",
        "format": "<span style='font-size:18px;font-weight:600;color:{{msg.payload==\"ON\"?\"#00ffaa\":\"#555\"}}'>{{msg.payload}}</span>",
        "layout": "row-spread",
        "className": "",
        "x": 370,
        "y": 760,
        "wires": []
    },
    {
        "id": "mqtt_fan_in",
        "type": "mqtt in",
        "z": "e6ecd1a3fd06e046",
        "name": "",
        "topic": "serre/fan",
        "qos": "2",
        "datatype": "auto-detect",
        "broker": "c73d35828f3586b6",
        "nl": false,
        "rap": true,
        "rh": 0,
        "inputs": 0,
        "x": 120,
        "y": 820,
        "wires": [["text_fan"]]
    },
    {
        "id": "text_fan",
        "type": "ui_text",
        "z": "e6ecd1a3fd06e046",
        "group": "group_systems",
        "order": 2,
        "width": "3",
        "height": "1",
        "name": "",
        "label": "🌀 Cooling Fan",
        "format": "<span style='font-size:18px;font-weight:600;color:{{msg.payload==\"ON\"?\"#00e5ff\":\"#555\"}}'>{{msg.payload}}</span>",
        "layout": "row-spread",
        "className": "",
        "x": 360,
        "y": 820,
        "wires": []
    },
    {
        "id": "2f938c3848900d98",
        "type": "mqtt in",
        "z": "e6ecd1a3fd06e046",
        "name": "",
        "topic": "serre/lightControl",
        "qos": "2",
        "datatype": "auto-detect",
        "broker": "c73d35828f3586b6",
        "nl": false,
        "rap": true,
        "rh": 0,
        "inputs": 0,
        "x": 140,
        "y": 880,
        "wires": [["3198f3c57e358cde"]]
    },
    {
        "id": "3198f3c57e358cde",
        "type": "ui_text",
        "z": "e6ecd1a3fd06e046",
        "group": "group_systems",
        "order": 3,
        "width": "3",
        "height": "1",
        "name": "",
        "label": "💡 Grow Lights",
        "format": "<span style='font-size:18px;font-weight:600;color:{{msg.payload==\"ON\"?\"#ffeb3b\":\"#555\"}}'>{{msg.payload}}</span>",
        "layout": "row-spread",
        "className": "",
        "x": 370,
        "y": 880,
        "wires": []
    },
    {
        "id": "mqtt_ventilation_in",
        "type": "mqtt in",
        "z": "e6ecd1a3fd06e046",
        "name": "",
        "topic": "serre/ventilation",
        "qos": "2",
        "datatype": "auto-detect",
        "broker": "c73d35828f3586b6",
        "nl": false,
        "rap": true,
        "rh": 0,
        "inputs": 0,
        "x": 140,
        "y": 940,
        "wires": [["text_ventilation"]]
    },
    {
        "id": "text_ventilation",
        "type": "ui_text",
        "z": "e6ecd1a3fd06e046",
        "group": "group_systems",
        "order": 4,
        "width": "3",
        "height": "1",
        "name": "",
        "label": "🌬️ Air Vent",
        "format": "<span style='font-size:18px;font-weight:600;color:{{msg.payload==\"ON\"?\"#00ffaa\":\"#555\"}}'>{{msg.payload}}</span>",
        "layout": "row-spread",
        "className": "",
        "x": 370,
        "y": 940,
        "wires": []
    },
    {
        "id": "switch_irrigation",
        "type": "ui_switch",
        "z": "e6ecd1a3fd06e046",
        "name": "",
        "label": "💦 Manual Irrigation Override",
        "tooltip": "Enable/Disable irrigation system manually",
        "group": "group_controls",
        "order": 1,
        "width": "6",
        "height": "1",
        "passthru": true,
        "decouple": "false",
        "topic": "topic",
        "topicType": "msg",
        "style": "",
        "onvalue": "ON",
        "onvalueType": "str",
        "onicon": "fa-tint",
        "oncolor": "#00ffaa",
        "offvalue": "OFF",
        "offvalueType": "str",
        "officon": "fa-tint-slash",
        "offcolor": "#333333",
        "animate": true,
        "className": "",
        "x": 180,
        "y": 1020,
        "wires": [["mqtt_irrigation_out"]]
    },
    {
        "id": "mqtt_irrigation_out",
        "type": "mqtt out",
        "z": "e6ecd1a3fd06e046",
        "name": "",
        "topic": "serre/irrigation",
        "qos": "",
        "retain": "",
        "respTopic": "",
        "contentType": "",
        "userProps": "",
        "correl": "",
        "expiry": "",
        "broker": "c73d35828f3586b6",
        "x": 430,
        "y": 1020,
        "wires": []
    }
]